decompress/__init__.py
decompress/edwards.py
decompress/libcurve25519.dylib
decompress/libcurve25519.so
tests/__init__.py
edwards-1.0.1.dist-info/LICENSE
edwards-1.0.1.dist-info/METADATA
edwards-1.0.1.dist-info/WHEEL
edwards-1.0.1.dist-info/top_level.txt
edwards-1.0.1.dist-info/RECORD
